setup.py
scripts/wnyc_backup_cull
scripts/wnyc_backup_upload
wnyc_backup/__init__.py
wnyc_backup.egg-info/PKG-INFO
wnyc_backup.egg-info/SOURCES.txt
wnyc_backup.egg-info/dependency_links.txt
wnyc_backup.egg-info/requires.txt
wnyc_backup.egg-info/top_level.txt
wnyc_backup.egg-info/zip-safe