Metadata-Version: 1.0
Name: wnyc-backup
Version: 0.0.3
Summary: Simple staggered backups
Home-page: http://github.com/wnyc/wnyc_backup
Author: Adam DePrince
Author-email: adeprince@nypublicradio.org
License: GPL
Platform: UNKNOWN
